slovene_g2p/SloveneG2P.py
slovene_g2p/__init__.py
slovene_g2p/resources/SloveneG2P_phoneme_set.json
slovene_g2p/resources/schwa_rules.tsv
slovene_g2p/resources/table_of_consonant_phonemes.tsv
slovene_g2p/resources/table_of_obstruent_conversions.tsv
slovene_g2p/resources/table_of_other_symbols.tsv
slovene_g2p/resources/table_of_vowel_phonemes.tsv
slovene_g2p-0.0.10.dist-info/LICENSE
slovene_g2p-0.0.10.dist-info/METADATA
slovene_g2p-0.0.10.dist-info/WHEEL
slovene_g2p-0.0.10.dist-info/top_level.txt
slovene_g2p-0.0.10.dist-info/RECORD
