Metadata-Version: 2.1
Name: slovene-g2p
Version: 0.0.10
Summary: rule based slovenian g2p
Home-page: UNKNOWN
Author: Peter Pisljar
License: UNKNOWN
Platform: UNKNOWN
Requires-Python: >=3.8.0, <3.12
License-File: LICENSE
